suchtree-1.3.dist-info/RECORD
suchtree-1.3.dist-info/WHEEL
suchtree-1.3.dist-info/top_level.txt
suchtree-1.3.dist-info/METADATA
suchtree-1.3.dist-info/licenses/LICENSE
SuchTree/MuchTree.c
SuchTree/MuchTree.pyx
SuchTree/__init__.py
SuchTree/__version__.py
SuchTree/MuchTree.cpython-311-darwin.so
SuchTree/exceptions.py
SuchTree/MuchTree.cpython-313-x86_64-linux-gnu.so
SuchTree/tests/links.csv
SuchTree/tests/lice.tree
SuchTree/tests/test.matrix
SuchTree/tests/support_int.tree
SuchTree/tests/support_float.tree
SuchTree/tests/test_SuchLinkedTrees.py
SuchTree/tests/gopher.tree
SuchTree/tests/test_SuchTree.py
SuchTree/tests/support_comment.tree
SuchTree/tests/test.tree
SuchTree/tests/test_new_api.py
