Metadata-Version: 2.4
Name: SuchTree
Version: 1.3
Summary: A python library for doing fast, thread-safe computations on phylogenetic trees
Author-email: Russell Neches <science@vort.org>
License-Expression: BSD-3-Clause
Project-URL: Homepage, https://github.com/ryneches/SuchTree
Keywords: biology,bio,phylogenetics,phylogeny,tree
Classifier: Programming Language :: Python :: 3
License-File: LICENSE
Requires-Dist: cython
Requires-Dist: numpy
Requires-Dist: scipy
Requires-Dist: pandas
Requires-Dist: dendropy
Dynamic: license-file
